<?xml version="1.0" encoding="utf-8"?><CatapultTargetIndex><IndexEntry><Entries><IndexEntry Term="&quot;The Criteria selection Like&quot; is not allowed when searching by Date."><Entries /><Links><IndexLink Title="&quot;Like&quot; is Not Allowed" Link="/Content/21CFR11 Message_Boxes/HIDP_LIKE_NOT_ALLOWED.htm#kanchor152" UsedConditions="" LocalConditions="" /></Links><SeeAlsoLinks /><IndexControlLinks /><SortAsLinks /></IndexEntry><IndexEntry Term="&amp;lt;NAME&amp;gt; data has been saved to &amp;lt;NAME&amp;gt;."><Entries /><Links><IndexLink Title="Data Saved" Link="/Content/21CFR11 Message_Boxes/HIDP_DATA_SAVED_TO_FILE.htm#kanchor126" UsedConditions="" LocalConditions="" /></Links><SeeAlsoLinks /><IndexControlLinks /><SortAsLinks /></IndexEntry><IndexEntry Term="A Password must be entered!"><Entries /><Links><IndexLink Title="Must Enter Password" Link="/Content/21CFR11 Message_Boxes/HIDP_MUST_ENTER_PASSWORD.htm#kanchor158" UsedConditions="" LocalConditions="" /></Links><SeeAlsoLinks /><IndexControlLinks /><SortAsLinks /></IndexEntry><IndexEntry Term="A required parameter is missing, therefore the data cannot be saved to the database."><Entries /><Links><IndexLink Title="Parameter Missing" Link="/Content/21CFR11 Message_Boxes/HIDP_INVALID_DATA.htm#kanchor174" UsedConditions="" LocalConditions="" /></Links><SeeAlsoLinks /><IndexControlLinks /><SortAsLinks /></IndexEntry><IndexEntry Term="A valid main window handler must be passed in order to login, therefore the login failed."><Entries /><Links><IndexLink Title="Window Handler Error" Link="/Content/21CFR11 Message_Boxes/HIDP_INVALID_WINHANDLER.htm#kanchor200" UsedConditions="" LocalConditions="" /></Links><SeeAlsoLinks /><IndexControlLinks /><SortAsLinks /></IndexEntry><IndexEntry Term="activities log"><Entries /><Links><IndexLink Title="Setting Up the System" Link="/Content/Setting_Up_the_System.htm#kanchor53" UsedConditions="" LocalConditions="" /></Links><SeeAlsoLinks /><IndexControlLinks /><SortAsLinks /></IndexEntry><IndexEntry Term="Advantage Integrity"><Entries><IndexEntry Term="introduction"><Entries /><Links><IndexLink Title="Welcome to Advantage Integrity Online Help" Link="/Content/Welcome_to_TA_Instruments_Advant.htm#kanchor1" UsedConditions="" LocalConditions="" /><IndexLink Title="Introducing the Advantage Integrity System" Link="/Content/Introducing_the_Advantage_Integrity_System.htm#kanchor3" UsedConditions="" LocalConditions="" /></Links><SeeAlsoLinks /><IndexControlLinks /><SortAsLinks /></IndexEntry><IndexEntry Term="TA System Manager"><Entries /><Links><IndexLink Title="Introducing the TA System Manager" Link="/Content/Introducing_the_TA_System_Manager.htm#kanchor23" UsedConditions="" LocalConditions="" /></Links><SeeAlsoLinks /><IndexControlLinks /><SortAsLinks /></IndexEntry></Entries><Links><IndexLink Title="Welcome to Advantage Integrity Online Help" Link="/Content/Welcome_to_TA_Instruments_Advant.htm#kanchor2" UsedConditions="" LocalConditions="" /></Links><SeeAlsoLinks /><IndexControlLinks /><SortAsLinks /></IndexEntry><IndexEntry Term="An unauthorized user with the user ID (NAME) has unsuccessfully tried to Login to the TA System Manager Account multiple times, therefore the operation was terminated."><Entries /><Links><IndexLink Title="Unknown User" Link="/Content/21CFR11 Message_Boxes/HIDP_UNKNOW_USER_LOGIN.htm#kanchor196" UsedConditions="" LocalConditions="" /></Links><SeeAlsoLinks /><IndexControlLinks /><SortAsLinks /></IndexEntry><IndexEntry Term="Are you sure you want to change the current status of  [Removed] for this account?"><Entries /><Links><IndexLink Title="Change Current Status?" Link="/Content/21CFR11 Message_Boxes/HIDP_SURE_TO_UNDELETE.htm#kanchor110" UsedConditions="" LocalConditions="" /></Links><SeeAlsoLinks /><IndexControlLinks /><SortAsLinks /></IndexEntry><IndexEntry Term="Are you sure you want to remove this item?"><Entries /><Links><IndexLink Title="Confirm Delete" Link="/Content/21CFR11 Message_Boxes/HIDP_SURE_TO_DELETE.htm#kanchor116" UsedConditions="" LocalConditions="" /></Links><SeeAlsoLinks /><IndexControlLinks /><SortAsLinks /></IndexEntry><IndexEntry Term="assigning users"><Entries /><Links><IndexLink Title="Introducing the TA System Manager" Link="/Content/Introducing_the_TA_System_Manager.htm#kanchor23" UsedConditions="" LocalConditions="" /></Links><SeeAlsoLinks /><IndexControlLinks /><SortAsLinks /></IndexEntry><IndexEntry Term="audit events"><Entries /><Links><IndexLink Title="Viewing the Audit Trail" Link="/Content/Viewing_the_Audit_Trail.htm#kanchor79" UsedConditions="" LocalConditions="" /></Links><SeeAlsoLinks /><IndexControlLinks /><SortAsLinks /></IndexEntry><IndexEntry Term="Audit Trail"><Entries><IndexEntry Term="adding a comment"><Entries /><Links><IndexLink Title="Adding Comments to the Audit Trail" Link="/Content/Adding_Comments_to_the_Audit_Trail.htm#kanchor82" UsedConditions="" LocalConditions="" /></Links><SeeAlsoLinks /><IndexControlLinks /><SortAsLinks /></IndexEntry><IndexEntry Term="exporting"><Entries /><Links><IndexLink Title="Exporting an Audit Trail" Link="/Content/Exporting_an_Audit_Trail.htm#kanchor83" UsedConditions="" LocalConditions="" /></Links><SeeAlsoLinks /><IndexControlLinks /><SortAsLinks /></IndexEntry><IndexEntry Term="viewing"><Entries /><Links><IndexLink Title="Viewing the Audit Trail" Link="/Content/Viewing_the_Audit_Trail.htm#kanchor76" UsedConditions="" LocalConditions="" /></Links><SeeAlsoLinks /><IndexControlLinks /><SortAsLinks /></IndexEntry></Entries><Links><IndexLink Title="Viewing the Audit Trail" Link="/Content/Viewing_the_Audit_Trail.htm#kanchor76" UsedConditions="" LocalConditions="" /></Links><SeeAlsoLinks /><IndexControlLinks /><SortAsLinks /></IndexEntry><IndexEntry Term="Audit Trail Viewer"><Entries><IndexEntry Term="browsing"><Entries /><Links><IndexLink Title="Viewing the Audit Trail" Link="/Content/Viewing_the_Audit_Trail.htm#kanchor77" UsedConditions="" LocalConditions="" /></Links><SeeAlsoLinks /><IndexControlLinks /><SortAsLinks /></IndexEntry><IndexEntry Term="organizing"><Entries /><Links><IndexLink Title="Viewing the Audit Trail" Link="/Content/Viewing_the_Audit_Trail.htm#kanchor81" UsedConditions="" LocalConditions="" /></Links><SeeAlsoLinks /><IndexControlLinks /><SortAsLinks /></IndexEntry><IndexEntry Term="sorting"><Entries /><Links><IndexLink Title="Sorting the Data in Tree View" Link="/Content/Sorting_the_Data_in_Tree_View.htm#kanchor70" UsedConditions="" LocalConditions="" /></Links><SeeAlsoLinks /><IndexControlLinks /><SortAsLinks /></IndexEntry></Entries><Links><IndexLink Title="Viewing the Audit Trail" Link="/Content/Viewing_the_Audit_Trail.htm#kanchor78" UsedConditions="" LocalConditions="" /></Links><SeeAlsoLinks /><IndexControlLinks /><SortAsLinks /></IndexEntry><IndexEntry Term="back up of database"><Entries /><Links><IndexLink Title="Backing Up the Database" Link="/Content/Backing_Up_the_Database.htm#kanchor84" UsedConditions="" LocalConditions="" /></Links><SeeAlsoLinks /><IndexControlLinks /><SortAsLinks /></IndexEntry><IndexEntry Term="Can not assign [MODULE] to any user since it is not enabled!"><Entries /><Links><IndexLink Title="Cannot Assign" Link="/Content/21CFR11 Message_Boxes/HIDP_NOT_AVAILABLE.htm#kanchor96" UsedConditions="" LocalConditions="" /></Links><SeeAlsoLinks /><IndexControlLinks /><SortAsLinks /></IndexEntry><IndexEntry Term="Cannot locate the data position when retrieving data from the source."><Entries /><Links><IndexLink Title="Cannot Locate Data Position" Link="/Content/21CFR11 Message_Boxes/HIDP_SEEK_FILE_POSITION_FAILED.htm#kanchor108" UsedConditions="" LocalConditions="" /></Links><SeeAlsoLinks /><IndexControlLinks /><SortAsLinks /></IndexEntry><IndexEntry Term="Changes have been made in the setup window. Do you want to save the changes?"><Entries /><Links><IndexLink Title="Save Setup Changes?" Link="/Content/21CFR11 Message_Boxes/HIDP_SAVE_CHANGES_PERMISSION.htm#kanchor186" UsedConditions="" LocalConditions="" /></Links><SeeAlsoLinks /><IndexControlLinks /><SortAsLinks /></IndexEntry><IndexEntry Term="clipboard"><Entries><IndexEntry Term="copying record ID"><Entries /><Links><IndexLink Title="Browsing the Database" Link="/Content/Browsing_the_Database.htm#kanchor62" UsedConditions="" LocalConditions="" /></Links><SeeAlsoLinks /><IndexControlLinks /><SortAsLinks /></IndexEntry></Entries><Links><IndexLink Title="Browsing the Database" Link="/Content/Browsing_the_Database.htm#kanchor67" UsedConditions="" LocalConditions="" /></Links><SeeAlsoLinks /><IndexControlLinks /><SortAsLinks /></IndexEntry><IndexEntry Term="closed system"><Entries /><Links><IndexLink Title="Introducing the Advantage Integrity System" Link="/Content/Introducing_the_Advantage_Integrity_System.htm#kanchor7" UsedConditions="" LocalConditions="" /></Links><SeeAlsoLinks /><IndexControlLinks /><SortAsLinks /></IndexEntry><IndexEntry Term="COM IDfaDataPtr Error!"><Entries /><Links><IndexLink Title="Communication Error" Link="/Content/21CFR11 Message_Boxes/HIDP_COM_ERROR.htm#kanchor113" UsedConditions="" LocalConditions="" /></Links><SeeAlsoLinks /><IndexControlLinks /><SortAsLinks /></IndexEntry><IndexEntry Term="comment"><Entries><IndexEntry Term="adding to Audit Trail"><Entries /><Links><IndexLink Title="Adding Comments to the Audit Trail" Link="/Content/Adding_Comments_to_the_Audit_Trail.htm#kanchor82" UsedConditions="" LocalConditions="" /></Links><SeeAlsoLinks /><IndexControlLinks /><SortAsLinks /></IndexEntry></Entries><Links><IndexLink Title="Adding Comments to the Audit Trail" Link="/Content/Adding_Comments_to_the_Audit_Trail.htm#kanchor82" UsedConditions="" LocalConditions="" /></Links><SeeAlsoLinks /><IndexControlLinks /><SortAsLinks /></IndexEntry><IndexEntry Term="Communication Error"><Entries /><Links><IndexLink Title="Communication Error" Link="/Content/21CFR11 Message_Boxes/HIDP_COM_ERROR.htm#kanchor112" UsedConditions="" LocalConditions="" /></Links><SeeAlsoLinks /><IndexControlLinks /><SortAsLinks /></IndexEntry><IndexEntry Term="configuring the instrument log"><Entries /><Links><IndexLink Title="Configuring the Instrument Log" Link="/Content/21CFR11 Message_Boxes/Configuring_the_Instrument_Log.htm#kanchor89" UsedConditions="" LocalConditions="" /></Links><SeeAlsoLinks /><IndexControlLinks /><SortAsLinks /></IndexEntry><IndexEntry Term="Confirm attribute changes"><Entries /><Links><IndexLink Title="Confirm Attribute Changes" Link="/Content/21CFR11 Message_Boxes/HIDP_CONFIRM_LEVEL_CHANGE_TITLE.htm#kanchor115" UsedConditions="" LocalConditions="" /></Links><SeeAlsoLinks /><IndexControlLinks /><SortAsLinks /></IndexEntry><IndexEntry Term="copy"><Entries><IndexEntry Term="Record ID to clipboard"><Entries /><Links><IndexLink Title="Browsing the Database" Link="/Content/Browsing_the_Database.htm#kanchor62" UsedConditions="" LocalConditions="" /></Links><SeeAlsoLinks /><IndexControlLinks /><SortAsLinks /></IndexEntry></Entries><Links><IndexLink Title="Browsing the Database" Link="/Content/Browsing_the_Database.htm#kanchor68" UsedConditions="" LocalConditions="" /></Links><SeeAlsoLinks /><IndexControlLinks /><SortAsLinks /></IndexEntry><IndexEntry Term="Could not load module &amp;lt;NAME&amp;gt;."><Entries /><Links><IndexLink Title="Could Not Load Module" Link="/Content/21CFR11 Message_Boxes/HIDP_IMPORT_MODULE_ERROR.htm#kanchor121" UsedConditions="" LocalConditions="" /></Links><SeeAlsoLinks /><IndexControlLinks /><SortAsLinks /></IndexEntry><IndexEntry Term="creating new user accounts"><Entries /><Links><IndexLink Title="Creating New User Accounts" Link="/Content/Creating_New_User_Accounts.htm#kanchor24" UsedConditions="" LocalConditions="" /></Links><SeeAlsoLinks /><IndexControlLinks /><SortAsLinks /></IndexEntry><IndexEntry Term="data"><Entries><IndexEntry Term="digitally verifying"><Entries /><Links><IndexLink Title="Digitally Verifying Data" Link="/Content/Digitally_Verifying_Data.htm#kanchor86" UsedConditions="" LocalConditions="" /></Links><SeeAlsoLinks /><IndexControlLinks /><SortAsLinks /></IndexEntry></Entries><Links><IndexLink Title="Digitally Verifying Data" Link="/Content/Digitally_Verifying_Data.htm#kanchor86" UsedConditions="" LocalConditions="" /></Links><SeeAlsoLinks /><IndexControlLinks /><SortAsLinks /></IndexEntry><IndexEntry Term="data analysis"><Entries><IndexEntry Term="using with Integrity"><Entries /><Links><IndexLink Title="Introducing the Advantage Integrity System" Link="/Content/Introducing_the_Advantage_Integrity_System.htm#kanchor3" UsedConditions="" LocalConditions="" /></Links><SeeAlsoLinks /><IndexControlLinks /><SortAsLinks /></IndexEntry></Entries><Links /><SeeAlsoLinks /><IndexControlLinks /><SortAsLinks /></IndexEntry><IndexEntry Term="data files"><Entries><IndexEntry Term="locating using the database viewer"><Entries /><Links><IndexLink Title="Browsing the Database" Link="/Content/Browsing_the_Database.htm#kanchor62" UsedConditions="" LocalConditions="" /></Links><SeeAlsoLinks /><IndexControlLinks /><SortAsLinks /></IndexEntry></Entries><Links><IndexLink Title="Browsing the Database" Link="/Content/Browsing_the_Database.htm#kanchor66" UsedConditions="" LocalConditions="" /></Links><SeeAlsoLinks /><IndexControlLinks /><SortAsLinks /></IndexEntry><IndexEntry Term="database"><Entries><IndexEntry Term="backup"><Entries /><Links><IndexLink Title="Backing Up the Database" Link="/Content/Backing_Up_the_Database.htm#kanchor85" UsedConditions="" LocalConditions="" /></Links><SeeAlsoLinks /><IndexControlLinks /><SortAsLinks /></IndexEntry><IndexEntry Term="connecting"><Entries /><Links><IndexLink Title="Using the Database Connection Wizard" Link="/Content/Using_the_Database_Connection_Wizard.htm#kanchor19" UsedConditions="" LocalConditions="" /></Links><SeeAlsoLinks /><IndexControlLinks /><SortAsLinks /></IndexEntry><IndexEntry Term="establishing"><Entries /><Links><IndexLink Title="Using the Database Setup Wizard" Link="/Content/Using_the_Database_Setup_Wizard.htm#kanchor21" UsedConditions="" LocalConditions="" /></Links><SeeAlsoLinks /><IndexControlLinks /><SortAsLinks /></IndexEntry><IndexEntry Term="restoring a record"><Entries /><Links><IndexLink Title="Restoring a Single Record" Link="/Content/Restoring_a_Single_Record.htm#kanchor73" UsedConditions="" LocalConditions="" /></Links><SeeAlsoLinks /><IndexControlLinks /><SortAsLinks /></IndexEntry><IndexEntry Term="setting up"><Entries /><Links><IndexLink Title="Using the Database Setup Wizard" Link="/Content/Using_the_Database_Setup_Wizard.htm#kanchor21" UsedConditions="" LocalConditions="" /></Links><SeeAlsoLinks /><IndexControlLinks /><SortAsLinks /></IndexEntry><IndexEntry Term="sorting"><Entries /><Links><IndexLink Title="Sorting the Data in Tree View" Link="/Content/Sorting_the_Data_in_Tree_View.htm#kanchor70" UsedConditions="" LocalConditions="" /></Links><SeeAlsoLinks /><IndexControlLinks /><SortAsLinks /></IndexEntry></Entries><Links><IndexLink Title="Using the Database Connection Wizard" Link="/Content/Using_the_Database_Connection_Wizard.htm#kanchor19" UsedConditions="" LocalConditions="" /><IndexLink Title="Browsing the Database" Link="/Content/Browsing_the_Database.htm#kanchor62" UsedConditions="" LocalConditions="" /><IndexLink Title="Restoring a Single Record" Link="/Content/Restoring_a_Single_Record.htm#kanchor74" UsedConditions="" LocalConditions="" /><IndexLink Title="Backing Up the Database" Link="/Content/Backing_Up_the_Database.htm#kanchor84" UsedConditions="" LocalConditions="" /></Links><SeeAlsoLinks /><IndexControlLinks /><SortAsLinks /></IndexEntry><IndexEntry Term="Database Connection Wizard"><Entries /><Links><IndexLink Title="Using the Database Connection Wizard" Link="/Content/Using_the_Database_Connection_Wizard.htm#kanchor19" UsedConditions="" LocalConditions="" /></Links><SeeAlsoLinks /><IndexControlLinks /><SortAsLinks /></IndexEntry><IndexEntry Term="database home position"><Entries /><Links><IndexLink Title="Setting the Database Home Position" Link="/Content/Setting_the_Database_Home_Position.htm#kanchor22" UsedConditions="" LocalConditions="" /></Links><SeeAlsoLinks /><IndexControlLinks /><SortAsLinks /></IndexEntry><IndexEntry Term="database information"><Entries /><Links><IndexLink Title="Setting Up the System" Link="/Content/Setting_Up_the_System.htm#kanchor44" UsedConditions="" LocalConditions="" /></Links><SeeAlsoLinks /><IndexControlLinks /><SortAsLinks /></IndexEntry><IndexEntry Term="Database open error. Please run the connection wizard to setup the connection to the database."><Entries /><Links><IndexLink Title="Database Open Error" Link="/Content/21CFR11 Message_Boxes/HIDP_DATABASE_OPEN_ERROR.htm#kanchor131" UsedConditions="" LocalConditions="" /></Links><SeeAlsoLinks /><IndexControlLinks /><SortAsLinks /></IndexEntry><IndexEntry Term="Database Search Wizard"><Entries /><Links><IndexLink Title="Using the Database Search Wizard" Link="/Content/Using_the_Database_Search_Wizard.htm#kanchor71" UsedConditions="" LocalConditions="" /></Links><SeeAlsoLinks /><IndexControlLinks /><SortAsLinks /></IndexEntry><IndexEntry Term="database searching by SQL"><Entries /><Links><IndexLink Title="Using the Database Search Wizard" Link="/Content/Using_the_Database_Search_Wizard.htm#kanchor71" UsedConditions="" LocalConditions="" /></Links><SeeAlsoLinks /><IndexControlLinks /><SortAsLinks /></IndexEntry><IndexEntry Term="Database Setup Wizard"><Entries /><Links><IndexLink Title="Using the Database Setup Wizard" Link="/Content/Using_the_Database_Setup_Wizard.htm#kanchor21" UsedConditions="" LocalConditions="" /></Links><SeeAlsoLinks /><IndexControlLinks /><SortAsLinks /></IndexEntry><IndexEntry Term="database viewer"><Entries><IndexEntry Term="browsing records"><Entries /><Links><IndexLink Title="Browsing the Database" Link="/Content/Browsing_the_Database.htm#kanchor62" UsedConditions="" LocalConditions="" /></Links><SeeAlsoLinks /><IndexControlLinks /><SortAsLinks /></IndexEntry><IndexEntry Term="organizing"><Entries /><Links><IndexLink Title="Browsing the Database" Link="/Content/Browsing_the_Database.htm#kanchor65" UsedConditions="" LocalConditions="" /></Links><SeeAlsoLinks /><IndexControlLinks /><SortAsLinks /></IndexEntry><IndexEntry Term="sorting"><Entries /><Links><IndexLink Title="Sorting the Data in Tree View" Link="/Content/Sorting_the_Data_in_Tree_View.htm#kanchor70" UsedConditions="" LocalConditions="" /></Links><SeeAlsoLinks /><IndexControlLinks /><SortAsLinks /></IndexEntry></Entries><Links><IndexLink Title="Browsing the Database" Link="/Content/Browsing_the_Database.htm#kanchor63" UsedConditions="" LocalConditions="" /><IndexLink Title="Restoring a Single Record" Link="/Content/Restoring_a_Single_Record.htm#kanchor73" UsedConditions="" LocalConditions="" /></Links><SeeAlsoLinks /><IndexControlLinks /><SortAsLinks /></IndexEntry><IndexEntry Term="database viewer options"><Entries /><Links><IndexLink Title="Setting the Database Home Position" Link="/Content/Setting_the_Database_Home_Position.htm#kanchor22" UsedConditions="" LocalConditions="" /></Links><SeeAlsoLinks /><IndexControlLinks /><SortAsLinks /></IndexEntry><IndexEntry Term="Databse Viewer"><Entries><IndexEntry Term="using to restore records"><Entries /><Links><IndexLink Title="Restoring a Single Record" Link="/Content/Restoring_a_Single_Record.htm#kanchor73" UsedConditions="" LocalConditions="" /></Links><SeeAlsoLinks /><IndexControlLinks /><SortAsLinks /></IndexEntry></Entries><Links><IndexLink Title="Restoring a Single Record" Link="/Content/Restoring_a_Single_Record.htm#kanchor73" UsedConditions="" LocalConditions="" /></Links><SeeAlsoLinks /><IndexControlLinks /><SortAsLinks /></IndexEntry><IndexEntry Term="description of system"><Entries /><Links><IndexLink Title="Introducing the Advantage Integrity System" Link="/Content/Introducing_the_Advantage_Integrity_System.htm#kanchor3" UsedConditions="" LocalConditions="" /></Links><SeeAlsoLinks /><IndexControlLinks /><SortAsLinks /></IndexEntry><IndexEntry Term="Deutsch"><Entries /><Links><IndexLink Title="Selecting a Language" Link="/Content/Selecting_a_Language.htm#kanchor18" UsedConditions="" LocalConditions="" /></Links><SeeAlsoLinks /><IndexControlLinks /><SortAsLinks /></IndexEntry><IndexEntry Term="digital verification of data"><Entries /><Links><IndexLink Title="Digitally Verifying Data" Link="/Content/Digitally_Verifying_Data.htm#kanchor86" UsedConditions="" LocalConditions="" /></Links><SeeAlsoLinks /><IndexControlLinks /><SortAsLinks /></IndexEntry><IndexEntry Term="DMA"><Entries><IndexEntry Term="assigning module privileges"><Entries /><Links><IndexLink Title="Adding Module Privileges" Link="/Content/Adding_Module_Privileges.htm#kanchor56" UsedConditions="" LocalConditions="" /></Links><SeeAlsoLinks /><IndexControlLinks /><SortAsLinks /></IndexEntry></Entries><Links><IndexLink Title="Adding Module Privileges" Link="/Content/Adding_Module_Privileges.htm#kanchor57" UsedConditions="" LocalConditions="" /></Links><SeeAlsoLinks /><IndexControlLinks /><SortAsLinks /></IndexEntry><IndexEntry Term="documentation"><Entries /><Links><IndexLink Title="Introducing the Advantage Integrity System" Link="/Content/Introducing_the_Advantage_Integrity_System.htm#kanchor4" UsedConditions="" LocalConditions="" /></Links><SeeAlsoLinks /><IndexControlLinks /><SortAsLinks /></IndexEntry><IndexEntry Term="electronic records"><Entries /><Links><IndexLink Title="Introducing the Advantage Integrity System" Link="/Content/Introducing_the_Advantage_Integrity_System.htm#kanchor5" UsedConditions="" LocalConditions="" /></Links><SeeAlsoLinks /><IndexControlLinks /><SortAsLinks /></IndexEntry><IndexEntry Term="English language selection"><Entries /><Links><IndexLink Title="Selecting a Language" Link="/Content/Selecting_a_Language.htm#kanchor17" UsedConditions="" LocalConditions="" /></Links><SeeAlsoLinks /><IndexControlLinks /><SortAsLinks /></IndexEntry><IndexEntry Term="error messages"><Entries /><Links><IndexLink Title="Using the Instrument Log" Link="/Content/21CFR11 Message_Boxes/Using_the_Instrument_Log.htm#kanchor87" UsedConditions="" LocalConditions="" /></Links><SeeAlsoLinks /><IndexControlLinks /><SortAsLinks /></IndexEntry><IndexEntry Term="exporting"><Entries><IndexEntry Term="Audit Trail"><Entries /><Links><IndexLink Title="Exporting an Audit Trail" Link="/Content/Exporting_an_Audit_Trail.htm#kanchor83" UsedConditions="" LocalConditions="" /></Links><SeeAlsoLinks /><IndexControlLinks /><SortAsLinks /></IndexEntry><IndexEntry Term="TA System Manager Log"><Entries /><Links><IndexLink Title="Exporting the System Manager Log" Link="/Content/Exporting_the_System_Manager_Log.htm#kanchor60" UsedConditions="" LocalConditions="" /></Links><SeeAlsoLinks /><IndexControlLinks /><SortAsLinks /></IndexEntry></Entries><Links><IndexLink Title="Exporting the System Manager Log" Link="/Content/Exporting_the_System_Manager_Log.htm#kanchor60" UsedConditions="" LocalConditions="" /></Links><SeeAlsoLinks /><IndexControlLinks /><SortAsLinks /></IndexEntry><IndexEntry Term="exporting an Audit Trail"><Entries /><Links><IndexLink Title="Exporting an Audit Trail" Link="/Content/Exporting_an_Audit_Trail.htm#kanchor83" UsedConditions="" LocalConditions="" /></Links><SeeAlsoLinks /><IndexControlLinks /><SortAsLinks /></IndexEntry><IndexEntry Term="fax numbers"><Entries /><Links><IndexLink Title="TA Instruments Offices" Link="/Content/TA_Instruments_Offices.htm#kanchor202" UsedConditions="" LocalConditions="" /></Links><SeeAlsoLinks /><IndexControlLinks /><SortAsLinks /></IndexEntry><IndexEntry Term="File &amp;lt;NAME&amp;gt; failed to open."><Entries /><Links><IndexLink Title="File Failed to Open" Link="/Content/21CFR11 Message_Boxes/HIDP_DATAFILE_OPEN_ERROR.htm#kanchor140" UsedConditions="" LocalConditions="" /></Links><SeeAlsoLinks /><IndexControlLinks /><SortAsLinks /></IndexEntry><IndexEntry Term="File &amp;lt;NAME&amp;gt; failed to open. Do you want to import the next file?"><Entries /><Links><IndexLink Title="File Open Failed. Import the Next File?" Link="/Content/21CFR11 Message_Boxes/HIDP_DATAFILE_OPEN_ERROR2.htm#kanchor141" UsedConditions="" LocalConditions="" /></Links><SeeAlsoLinks /><IndexControlLinks /><SortAsLinks /></IndexEntry><IndexEntry Term="File Error"><Entries /><Links><IndexLink Title="File Error" Link="/Content/21CFR11 Message_Boxes/HIDP_FILE_ERROR.htm#kanchor139" UsedConditions="" LocalConditions="" /></Links><SeeAlsoLinks /><IndexControlLinks /><SortAsLinks /></IndexEntry><IndexEntry Term="following the audit trail"><Entries /><Links><IndexLink Title="Viewing the Audit Trail" Link="/Content/Viewing_the_Audit_Trail.htm#kanchor76" UsedConditions="" LocalConditions="" /></Links><SeeAlsoLinks /><IndexControlLinks /><SortAsLinks /></IndexEntry><IndexEntry Term="Food and Drug Administration (FDA)"><Entries /><Links><IndexLink Title="Introducing the Advantage Integrity System" Link="/Content/Introducing_the_Advantage_Integrity_System.htm#kanchor6" UsedConditions="" LocalConditions="" /></Links><SeeAlsoLinks /><IndexControlLinks /><SortAsLinks /></IndexEntry></Entries></IndexEntry></CatapultTargetIndex>